embodyble/__init__.py
embodyble/__main__.py
embodyble/cli.py
embodyble/embodyble.py
embodyble/exceptions.py
embodyble/listeners.py
embodyble/logging.py
embodyble/py.typed
embodyble/reporting.py
embodyble/utils.py
embody_ble-1.1.26.dist-info/METADATA
embody_ble-1.1.26.dist-info/WHEEL
embody_ble-1.1.26.dist-info/entry_points.txt
embody_ble-1.1.26.dist-info/licenses/LICENSE
embody_ble-1.1.26.dist-info/RECORD
