Metadata-Version: 2.4
Name: embody-ble
Version: 1.1.26
Summary: Communicate with the EmBody device over BLE (bluetooth)
Project-URL: Homepage, https://github.com/aidee-health/embody-ble
Project-URL: Repository, https://github.com/aidee-health/embody-ble
Project-URL: Changelog, https://github.com/aidee-health/embody-ble/releases
Author-email: Aidee Health AS <hello@aidee.io>
License-Expression: MIT
License-File: LICENSE
Classifier: Development Status :: 5 - Production/Stable
Requires-Python: <4.0,>=3.11
Requires-Dist: bleak>=0.22.3
Requires-Dist: embody-codec>=1.0.32
Requires-Dist: embody-serial>=1.0.34
